{
  "meta": {
    "source_file": "./data/dss1red-fits/dss1red_XE505.fits",
    "exported_utc": "2026-02-04T15:23:29.545325+00:00",
    "size_bytes": 391985280
  },
  "header": {
    "SIMPLE": true,
    "BITPIX": 16,
    "NAXIS": 2,
    "NAXIS1": 14000,
    "NAXIS2": 13999,
    "DATE": "2006-04-04T16:04:11",
    "ORIGIN": "STScI/MAST",
    "SURVEY": "POSSI-E",
    "REGION": "XE505",
    "PLATEID": "08ZK",
    "SCANNUM": "00",
    "DSCNDNUM": "00",
    "TELESCID": 1,
    "BANDPASS": 8,
    "COPYRGHT": "STScI/AURA",
    "SITELAT": 33.356,
    "SITELONG": 116.863,
    "TELESCOP": "Palomar Schmidt",
    "INSTRUME": "Photographic Plate",
    "EMULSION": "103aE",
    "FILTER": "plexi",
    "PLTSCALE": 67.2,
    "PLTSIZEX": 355.0,
    "PLTSIZEY": 355.0,
    "PLATERA": 247.701324606,
    "PLATEDEC": 11.6826279142,
    "PLTLABEL": "E1372",
    "DATE-OBS": "1955-03-26T11:48:00",
    "EXPOSURE": 50.0,
    "PLTGRADE": "1",
    "OBSHA": 0.516667,
    "OBSZD": 22.7723,
    "AIRMASS": 1.08434,
    "REFBETA": 61.8196598237,
    "REFBETAP": -0.082,
    "REFK1": -4854.48197869,
    "REFK2": 0.0,
    "CNPIX1": 0,
    "CNPIX2": 0,
    "XPIXELS": 14000,
    "YPIXELS": 13999,
    "XPIXELSZ": 25.2845,
    "YPIXELSZ": 25.2845,
    "PPO1": 0.0,
    "PPO2": 0.0,
    "PPO3": 177500.0,
    "PPO4": 0.0,
    "PPO5": 0.0,
    "PPO6": 177500.0,
    "PLTRAH": 16,
    "PLTRAM": 30,
    "PLTRAS": 48.32,
    "PLTDECSN": "+",
    "PLTDECD": 11,
    "PLTDECM": 40,
    "PLTDECS": 57.5,
    "EQUINOX": 2000.0,
    "AMDX1": 67.2541018865,
    "AMDX2": -0.050374381431,
    "AMDX3": -144.535313972,
    "AMDX4": -1.7754651823e-05,
    "AMDX5": -4.68699896186e-05,
    "AMDX6": 1.70738147444e-07,
    "AMDX7": 0.0,
    "AMDX8": 2.18464320686e-06,
    "AMDX9": -9.24147474972e-08,
    "AMDX10": 2.3586396581e-06,
    "AMDX11": 1.95485607367e-08,
    "AMDX12": 0.0,
    "AMDX13": 0.0,
    "AMDX14": 0.0,
    "AMDX15": 0.0,
    "AMDX16": 0.0,
    "AMDX17": 0.0,
    "AMDX18": 0.0,
    "AMDX19": 0.0,
    "AMDX20": 0.0,
    "AMDY1": 67.272571604,
    "AMDY2": 0.0446627231465,
    "AMDY3": -187.468137481,
    "AMDY4": -3.70976475611e-05,
    "AMDY5": -3.5472666737e-06,
    "AMDY6": -6.94304425684e-07,
    "AMDY7": 0.0,
    "AMDY8": 2.07393724393e-06,
    "AMDY9": 6.30819753369e-09,
    "AMDY10": 2.32273012977e-06,
    "AMDY11": 3.09882742054e-08,
    "AMDY12": 0.0,
    "AMDY13": 0.0,
    "AMDY14": 0.0,
    "AMDY15": 0.0,
    "AMDY16": 0.0,
    "AMDY17": 0.0,
    "AMDY18": 0.0,
    "AMDY19": 0.0,
    "AMDY20": 0.0,
    "AMDREX1": 67.25369309,
    "AMDREX2": -0.0499423791776,
    "AMDREX3": -144.550820786,
    "AMDREX4": -1.30493774331e-06,
    "AMDREX5": -3.24407182405e-05,
    "AMDREX6": 5.37620562759e-06,
    "AMDREX7": 0.0,
    "AMDREX8": -1.95777363465e-07,
    "AMDREX9": -7.95524971913e-08,
    "AMDREX10": -2.16496572643e-08,
    "AMDREX11": 1.85397004487e-08,
    "AMDREX12": 0.0,
    "AMDREX13": 0.0,
    "AMDREX14": 0.0,
    "AMDREX15": 0.0,
    "AMDREX16": 0.0,
    "AMDREX17": 0.0,
    "AMDREX18": 0.0,
    "AMDREX19": 0.0,
    "AMDREX20": 0.0,
    "AMDREY1": 67.2690330209,
    "AMDREY2": 0.0448597049355,
    "AMDREY3": -187.469574231,
    "AMDREY4": -1.33668699609e-05,
    "AMDREY5": 7.1930196236e-06,
    "AMDREY6": 7.75221290764e-06,
    "AMDREY7": 0.0,
    "AMDREY8": -2.99411796703e-07,
    "AMDREY9": 1.08995443993e-09,
    "AMDREY10": -7.77998749705e-08,
    "AMDREY11": 1.88661160515e-08,
    "AMDREY12": 0.0,
    "AMDREY13": 0.0,
    "AMDREY14": 0.0,
    "AMDREY15": 0.0,
    "AMDREY16": 0.0,
    "AMDREY17": 0.0,
    "AMDREY18": 0.0,
    "AMDREY19": 0.0,
    "AMDREY20": 0.0,
    "ASTRMASK": "xe.mask"
  }
}