{
  "meta": {
    "source_file": "./data/dss1red-fits/dss1red_XE690.fits",
    "exported_utc": "2026-02-04T15:23:26.820281+00:00",
    "size_bytes": 391985280
  },
  "header": {
    "SIMPLE": true,
    "BITPIX": 16,
    "NAXIS": 2,
    "NAXIS1": 14000,
    "NAXIS2": 13999,
    "DATE": "2006-04-04T16:05:53",
    "ORIGIN": "STScI/MAST",
    "SURVEY": "POSSI-E",
    "REGION": "XE690",
    "PLATEID": "0E1Z",
    "SCANNUM": "00",
    "DSCNDNUM": "00",
    "TELESCID": 1,
    "BANDPASS": 8,
    "COPYRGHT": "STScI/AURA",
    "SITELAT": 33.356,
    "SITELONG": 116.863,
    "TELESCOP": "Palomar Schmidt",
    "INSTRUME": "Photographic Plate",
    "EMULSION": "103aE",
    "FILTER": "plexi",
    "PLTSCALE": 67.2,
    "PLTSIZEX": 355.0,
    "PLTSIZEY": 355.0,
    "PLATERA": 277.940506951,
    "PLATEDEC": -5.90202521828,
    "PLTLABEL": "E300",
    "DATE-OBS": "1951-08-04T06:08:00",
    "EXPOSURE": 50.0,
    "PLTGRADE": "2",
    "OBSHA": -0.283333,
    "OBSZD": 39.4709,
    "AIRMASS": 1.29452,
    "REFBETA": 61.8196598237,
    "REFBETAP": -0.082,
    "REFK1": 41290.3784636,
    "REFK2": 0.0,
    "CNPIX1": 0,
    "CNPIX2": 0,
    "XPIXELS": 14000,
    "YPIXELS": 13999,
    "XPIXELSZ": 25.2845,
    "YPIXELSZ": 25.2845,
    "PPO1": 0.0,
    "PPO2": 0.0,
    "PPO3": 177500.0,
    "PPO4": 0.0,
    "PPO5": 0.0,
    "PPO6": 177500.0,
    "PLTRAH": 18,
    "PLTRAM": 31,
    "PLTRAS": 45.72,
    "PLTDECSN": "-",
    "PLTDECD": 5,
    "PLTDECM": 54,
    "PLTDECS": 7.3,
    "EQUINOX": 2000.0,
    "AMDX1": 67.2422883832,
    "AMDX2": 0.0473219422312,
    "AMDX3": -251.822898679,
    "AMDX4": -2.30644763872e-05,
    "AMDX5": 2.38871531207e-06,
    "AMDX6": -1.75551721851e-05,
    "AMDX7": 0.0,
    "AMDX8": 2.1849173401e-06,
    "AMDX9": -1.04984435305e-07,
    "AMDX10": 2.52860791573e-06,
    "AMDX11": -8.93732086075e-09,
    "AMDX12": 0.0,
    "AMDX13": 0.0,
    "AMDX14": 0.0,
    "AMDX15": 0.0,
    "AMDX16": 0.0,
    "AMDX17": 0.0,
    "AMDX18": 0.0,
    "AMDX19": 0.0,
    "AMDX20": 0.0,
    "AMDY1": 67.2706117944,
    "AMDY2": -0.0594348691302,
    "AMDY3": 82.6066580345,
    "AMDY4": -1.93339044667e-06,
    "AMDY5": -1.06615312376e-05,
    "AMDY6": -5.14455695894e-06,
    "AMDY7": 0.0,
    "AMDY8": 2.14270944547e-06,
    "AMDY9": 4.28702127046e-08,
    "AMDY10": 2.37786037688e-06,
    "AMDY11": -2.0763389028e-09,
    "AMDY12": 0.0,
    "AMDY13": 0.0,
    "AMDY14": 0.0,
    "AMDY15": 0.0,
    "AMDY16": 0.0,
    "AMDY17": 0.0,
    "AMDY18": 0.0,
    "AMDY19": 0.0,
    "AMDY20": 0.0,
    "AMDREX1": 67.2420938566,
    "AMDREX2": 0.0402186734092,
    "AMDREX3": -251.869441161,
    "AMDREX4": 7.01464869801e-06,
    "AMDREX5": -4.52602724051e-06,
    "AMDREX6": -4.70789428885e-06,
    "AMDREX7": 0.0,
    "AMDREX8": -2.02714366459e-07,
    "AMDREX9": -1.06790945118e-07,
    "AMDREX10": 1.26237285675e-07,
    "AMDREX11": 3.12300353676e-08,
    "AMDREX12": 0.0,
    "AMDREX13": 0.0,
    "AMDREX14": 0.0,
    "AMDREX15": 0.0,
    "AMDREX16": 0.0,
    "AMDREX17": 0.0,
    "AMDREX18": 0.0,
    "AMDREX19": 0.0,
    "AMDREX20": 0.0,
    "AMDREY1": 67.2575656364,
    "AMDREY2": -0.0596252942333,
    "AMDREY3": 82.6552017172,
    "AMDREY4": -3.27778452445e-06,
    "AMDREY5": 9.49387016898e-06,
    "AMDREY6": -4.66603127298e-06,
    "AMDREY7": 0.0,
    "AMDREY8": -2.59337176824e-07,
    "AMDREY9": 5.26608896446e-08,
    "AMDREY10": -3.33457990583e-09,
    "AMDREY11": 1.36312528355e-08,
    "AMDREY12": 0.0,
    "AMDREY13": 0.0,
    "AMDREY14": 0.0,
    "AMDREY15": 0.0,
    "AMDREY16": 0.0,
    "AMDREY17": 0.0,
    "AMDREY18": 0.0,
    "AMDREY19": 0.0,
    "AMDREY20": 0.0,
    "ASTRMASK": "xe.mask"
  }
}