{
  "meta": {
    "source_file": "./data/dss1red-fits/dss1red_XE098.fits",
    "exported_utc": "2026-02-04T15:23:16.397472+00:00",
    "size_bytes": 391985280
  },
  "header": {
    "SIMPLE": true,
    "BITPIX": 16,
    "NAXIS": 2,
    "NAXIS1": 14000,
    "NAXIS2": 13999,
    "DATE": "2006-04-04T16:01:39",
    "ORIGIN": "STScI/MAST",
    "SURVEY": "POSSI-E",
    "REGION": "XE098",
    "PLATEID": "07NT",
    "SCANNUM": "00",
    "DSCNDNUM": "00",
    "TELESCID": 1,
    "BANDPASS": 8,
    "COPYRGHT": "STScI/AURA",
    "SITELAT": 33.356,
    "SITELONG": 116.863,
    "TELESCOP": "Palomar Schmidt",
    "INSTRUME": "Photographic Plate",
    "EMULSION": "103aE",
    "FILTER": "plexi",
    "PLTSCALE": 67.2,
    "PLTSIZEX": 355.0,
    "PLTSIZEY": 355.0,
    "PLATERA": 220.960332219,
    "PLATEDEC": 59.3859762555,
    "PLTLABEL": "E1425",
    "DATE-OBS": "1955-03-16T11:25:00",
    "EXPOSURE": 50.0,
    "PLTGRADE": "1",
    "OBSHA": -0.35,
    "OBSZD": 26.3254,
    "AIRMASS": 1.11543,
    "REFBETA": 61.8196598237,
    "REFBETAP": -0.082,
    "REFK1": 38593.8418892,
    "REFK2": 0.0,
    "CNPIX1": 0,
    "CNPIX2": 0,
    "XPIXELS": 14000,
    "YPIXELS": 13999,
    "XPIXELSZ": 25.2845,
    "YPIXELSZ": 25.2845,
    "PPO1": 0.0,
    "PPO2": 0.0,
    "PPO3": 177500.0,
    "PPO4": 0.0,
    "PPO5": 0.0,
    "PPO6": 177500.0,
    "PLTRAH": 14,
    "PLTRAM": 43,
    "PLTRAS": 50.48,
    "PLTDECSN": "+",
    "PLTDECD": 59,
    "PLTDECM": 23,
    "PLTDECS": 9.5,
    "EQUINOX": 2000.0,
    "AMDX1": 67.2466795055,
    "AMDX2": -0.189378767528,
    "AMDX3": -179.714169175,
    "AMDX4": -1.01681693729e-05,
    "AMDX5": -3.77562041332e-06,
    "AMDX6": -2.93224824452e-06,
    "AMDX7": 0.0,
    "AMDX8": 1.95951252155e-06,
    "AMDX9": -8.16984372201e-08,
    "AMDX10": 2.0851318433e-06,
    "AMDX11": -1.40729027171e-07,
    "AMDX12": 0.0,
    "AMDX13": 0.0,
    "AMDX14": 0.0,
    "AMDX15": 0.0,
    "AMDX16": 0.0,
    "AMDX17": 0.0,
    "AMDX18": 0.0,
    "AMDX19": 0.0,
    "AMDX20": 0.0,
    "AMDY1": 67.2648580267,
    "AMDY2": 0.184052816669,
    "AMDY3": 156.434207805,
    "AMDY4": 1.39466627805e-05,
    "AMDY5": -3.27293515922e-06,
    "AMDY6": 2.93729193776e-07,
    "AMDY7": 0.0,
    "AMDY8": 1.83423013578e-06,
    "AMDY9": -1.6071097632e-07,
    "AMDY10": 2.02674002644e-06,
    "AMDY11": -6.5437718143e-08,
    "AMDY12": 0.0,
    "AMDY13": 0.0,
    "AMDY14": 0.0,
    "AMDY15": 0.0,
    "AMDY16": 0.0,
    "AMDY17": 0.0,
    "AMDY18": 0.0,
    "AMDY19": 0.0,
    "AMDY20": 0.0,
    "AMDREX1": 67.2457029524,
    "AMDREX2": -0.186328867969,
    "AMDREX3": -180.964224703,
    "AMDREX4": 1.2430625771e-05,
    "AMDREX5": -5.22682827972e-06,
    "AMDREX6": 4.51425347384e-06,
    "AMDREX7": 0.0,
    "AMDREX8": -3.06597348523e-07,
    "AMDREX9": -1.43227060218e-07,
    "AMDREX10": -1.87380167046e-07,
    "AMDREX11": -1.67723303502e-10,
    "AMDREX12": 0.0,
    "AMDREX13": 0.0,
    "AMDREX14": 0.0,
    "AMDREX15": 0.0,
    "AMDREX16": 0.0,
    "AMDREX17": 0.0,
    "AMDREX18": 0.0,
    "AMDREX19": 0.0,
    "AMDREX20": 0.0,
    "AMDREY1": 67.2599926572,
    "AMDREY2": 0.1839990031,
    "AMDREY3": 158.154221782,
    "AMDREY4": -1.42936050271e-05,
    "AMDREY5": 1.78210050168e-05,
    "AMDREY6": -5.06435194999e-06,
    "AMDREY7": 0.0,
    "AMDREY8": -4.23648242237e-07,
    "AMDREY9": -5.97064399994e-08,
    "AMDREY10": -2.35062012296e-07,
    "AMDREY11": -4.65943805915e-08,
    "AMDREY12": 0.0,
    "AMDREY13": 0.0,
    "AMDREY14": 0.0,
    "AMDREY15": 0.0,
    "AMDREY16": 0.0,
    "AMDREY17": 0.0,
    "AMDREY18": 0.0,
    "AMDREY19": 0.0,
    "AMDREY20": 0.0,
    "ASTRMASK": "xe.mask"
  }
}