{
  "meta": {
    "source_file": "./data/dss1red-fits/dss1red_XE183.fits",
    "exported_utc": "2026-02-04T15:23:20.841011+00:00",
    "size_bytes": 391985280
  },
  "header": {
    "SIMPLE": true,
    "BITPIX": 16,
    "NAXIS": 2,
    "NAXIS1": 14000,
    "NAXIS2": 13999,
    "DATE": "2006-04-04T16:02:22",
    "ORIGIN": "STScI/MAST",
    "SURVEY": "POSSI-E",
    "REGION": "XE183",
    "PLATEID": "07W1",
    "SCANNUM": "00",
    "DSCNDNUM": "00",
    "TELESCID": 1,
    "BANDPASS": 8,
    "COPYRGHT": "STScI/AURA",
    "SITELAT": 33.356,
    "SITELONG": 116.863,
    "TELESCOP": "Palomar Schmidt",
    "INSTRUME": "Photographic Plate",
    "EMULSION": "103aE",
    "FILTER": "plexi",
    "PLTSCALE": 67.2,
    "PLTSIZEX": 355.0,
    "PLTSIZEY": 355.0,
    "PLATERA": 290.007823595,
    "PLATEDEC": 48.2695418668,
    "PLTLABEL": "E814",
    "DATE-OBS": "1953-09-08T03:57:00",
    "EXPOSURE": 45.0,
    "PLTGRADE": "1",
    "OBSHA": 0.416667,
    "OBSZD": 15.6051,
    "AIRMASS": 1.03819,
    "REFBETA": 61.8196598237,
    "REFBETAP": -0.082,
    "REFK1": -1946.43270999,
    "REFK2": 0.0,
    "CNPIX1": 0,
    "CNPIX2": 0,
    "XPIXELS": 14000,
    "YPIXELS": 13999,
    "XPIXELSZ": 25.2845,
    "YPIXELSZ": 25.2845,
    "PPO1": 0.0,
    "PPO2": 0.0,
    "PPO3": 177500.0,
    "PPO4": 0.0,
    "PPO5": 0.0,
    "PPO6": 177500.0,
    "PLTRAH": 19,
    "PLTRAM": 20,
    "PLTRAS": 1.88,
    "PLTDECSN": "+",
    "PLTDECD": 48,
    "PLTDECM": 16,
    "PLTDECS": 10.4,
    "EQUINOX": 2000.0,
    "AMDX1": 67.2478071887,
    "AMDX2": 0.0429814229897,
    "AMDX3": -370.143278733,
    "AMDX4": -1.00794215255e-05,
    "AMDX5": 1.38046667611e-05,
    "AMDX6": 1.45861190363e-06,
    "AMDX7": 0.0,
    "AMDX8": 1.76104124797e-06,
    "AMDX9": -9.81128000611e-08,
    "AMDX10": 2.2311271087e-06,
    "AMDX11": -2.66926251839e-08,
    "AMDX12": 0.0,
    "AMDX13": 0.0,
    "AMDX14": 0.0,
    "AMDX15": 0.0,
    "AMDX16": 0.0,
    "AMDX17": 0.0,
    "AMDX18": 0.0,
    "AMDX19": 0.0,
    "AMDX20": 0.0,
    "AMDY1": 67.2652748711,
    "AMDY2": -0.0451400668325,
    "AMDY3": 89.8601124787,
    "AMDY4": 7.84631444423e-06,
    "AMDY5": -4.34913966805e-05,
    "AMDY6": 3.8741768163e-07,
    "AMDY7": 0.0,
    "AMDY8": 1.74441605744e-06,
    "AMDY9": -1.71837494325e-08,
    "AMDY10": 2.32496386735e-06,
    "AMDY11": -1.97486588518e-08,
    "AMDY12": 0.0,
    "AMDY13": 0.0,
    "AMDY14": 0.0,
    "AMDY15": 0.0,
    "AMDY16": 0.0,
    "AMDY17": 0.0,
    "AMDY18": 0.0,
    "AMDY19": 0.0,
    "AMDY20": 0.0,
    "AMDREX1": 67.2440762141,
    "AMDREX2": 0.0418648166846,
    "AMDREX3": -371.666125309,
    "AMDREX4": 1.96380448784e-05,
    "AMDREX5": 1.03113950874e-06,
    "AMDREX6": 5.44252800248e-06,
    "AMDREX7": 0.0,
    "AMDREX8": -2.98718623321e-07,
    "AMDREX9": -1.0074526335e-07,
    "AMDREX10": 6.742996652e-08,
    "AMDREX11": 2.3356896878e-08,
    "AMDREX12": 0.0,
    "AMDREX13": 0.0,
    "AMDREX14": 0.0,
    "AMDREX15": 0.0,
    "AMDREX16": 0.0,
    "AMDREX17": 0.0,
    "AMDREX18": 0.0,
    "AMDREX19": 0.0,
    "AMDREX20": 0.0,
    "AMDREY1": 67.2610715343,
    "AMDREY2": -0.0460447173855,
    "AMDREY3": 91.4508075275,
    "AMDREY4": -3.04827094441e-06,
    "AMDREY5": -7.10257472653e-06,
    "AMDREY6": -2.26385499115e-06,
    "AMDREY7": 0.0,
    "AMDREY8": -2.65716365821e-07,
    "AMDREY9": -2.30628322305e-08,
    "AMDREY10": 1.26630603913e-08,
    "AMDREY11": 3.76872239372e-08,
    "AMDREY12": 0.0,
    "AMDREY13": 0.0,
    "AMDREY14": 0.0,
    "AMDREY15": 0.0,
    "AMDREY16": 0.0,
    "AMDREY17": 0.0,
    "AMDREY18": 0.0,
    "AMDREY19": 0.0,
    "AMDREY20": 0.0,
    "ASTRMASK": "xe.mask"
  }
}