{
  "meta": {
    "source_file": "./data/dss1red-fits/dss1red_XE121.fits",
    "exported_utc": "2026-02-04T15:23:25.201928+00:00",
    "size_bytes": 391985280
  },
  "header": {
    "SIMPLE": true,
    "BITPIX": 16,
    "NAXIS": 2,
    "NAXIS1": 14000,
    "NAXIS2": 13999,
    "DATE": "2006-04-04T16:01:49",
    "ORIGIN": "STScI/MAST",
    "SURVEY": "POSSI-E",
    "REGION": "XE121",
    "PLATEID": "07P4",
    "SCANNUM": "00",
    "DSCNDNUM": "00",
    "TELESCID": 1,
    "BANDPASS": 8,
    "COPYRGHT": "STScI/AURA",
    "SITELAT": 33.356,
    "SITELONG": 116.863,
    "TELESCOP": "Palomar Schmidt",
    "INSTRUME": "Photographic Plate",
    "EMULSION": "103aE",
    "FILTER": "plexi",
    "PLTSCALE": 67.2,
    "PLTSIZEX": 355.0,
    "PLTSIZEY": 355.0,
    "PLATERA": 97.9589990934,
    "PLATEDEC": 53.9088941013,
    "PLTLABEL": "E984",
    "DATE-OBS": "1954-02-24T04:08:00",
    "EXPOSURE": 40.0,
    "PLTGRADE": "1",
    "OBSHA": -0.116667,
    "OBSZD": 20.5984,
    "AIRMASS": 1.06814,
    "REFBETA": 61.8196598237,
    "REFBETAP": -0.082,
    "REFK1": 21705.5110975,
    "REFK2": 0.0,
    "CNPIX1": 0,
    "CNPIX2": 0,
    "XPIXELS": 14000,
    "YPIXELS": 13999,
    "XPIXELSZ": 25.2845,
    "YPIXELSZ": 25.2845,
    "PPO1": 0.0,
    "PPO2": 0.0,
    "PPO3": 177500.0,
    "PPO4": 0.0,
    "PPO5": 0.0,
    "PPO6": 177500.0,
    "PLTRAH": 6,
    "PLTRAM": 31,
    "PLTRAS": 50.16,
    "PLTDECSN": "+",
    "PLTDECD": 53,
    "PLTDECM": 54,
    "PLTDECS": 32.0,
    "EQUINOX": 2000.0,
    "AMDX1": 67.23645,
    "AMDX2": 0.7576036,
    "AMDX3": -236.7115,
    "AMDX4": -2.619773e-05,
    "AMDX5": -3.55605e-05,
    "AMDX6": 0.0,
    "AMDX7": 0.0,
    "AMDX8": 0.0,
    "AMDX9": 0.0,
    "AMDX10": 0.0,
    "AMDX11": 0.0,
    "AMDX12": 2.070391e-06,
    "AMDX13": 0.0,
    "AMDX14": 0.0,
    "AMDX15": 0.0,
    "AMDX16": 0.0,
    "AMDX17": 0.0,
    "AMDX18": 0.0,
    "AMDX19": 0.0,
    "AMDX20": 0.0,
    "AMDY1": 67.25112,
    "AMDY2": -0.7616956,
    "AMDY3": -137.8616,
    "AMDY4": -3.50348e-05,
    "AMDY5": -7.573662e-06,
    "AMDY6": 0.0,
    "AMDY7": 0.0,
    "AMDY8": 0.0,
    "AMDY9": 0.0,
    "AMDY10": 0.0,
    "AMDY11": 0.0,
    "AMDY12": 1.950037e-06,
    "AMDY13": 0.0,
    "AMDY14": 0.0,
    "AMDY15": 0.0,
    "AMDY16": 0.0,
    "AMDY17": 0.0,
    "AMDY18": 0.0,
    "AMDY19": 0.0,
    "AMDY20": 0.0,
    "AMDREX1": 67.234961563,
    "AMDREX2": 0.755888212168,
    "AMDREX3": -238.220613414,
    "AMDREX4": 2.66329954916e-06,
    "AMDREX5": -1.8717713762e-05,
    "AMDREX6": -1.3120732102e-06,
    "AMDREX7": 0.0,
    "AMDREX8": -3.94917988516e-07,
    "AMDREX9": 5.4059984319e-08,
    "AMDREX10": -4.94569277169e-08,
    "AMDREX11": 7.0943283358e-08,
    "AMDREX12": 0.0,
    "AMDREX13": 0.0,
    "AMDREX14": 0.0,
    "AMDREX15": 0.0,
    "AMDREX16": 0.0,
    "AMDREX17": 0.0,
    "AMDREX18": 0.0,
    "AMDREX19": 0.0,
    "AMDREX20": 0.0,
    "AMDREY1": 67.2470314048,
    "AMDREY2": -0.762062393771,
    "AMDREY3": -136.056255781,
    "AMDREY4": -2.73569274479e-05,
    "AMDREY5": 3.49972070036e-06,
    "AMDREY6": 1.04548301191e-05,
    "AMDREY7": 0.0,
    "AMDREY8": -4.48756722278e-07,
    "AMDREY9": 3.83076892132e-08,
    "AMDREY10": -1.72894345621e-07,
    "AMDREY11": 3.22207516324e-08,
    "AMDREY12": 0.0,
    "AMDREY13": 0.0,
    "AMDREY14": 0.0,
    "AMDREY15": 0.0,
    "AMDREY16": 0.0,
    "AMDREY17": 0.0,
    "AMDREY18": 0.0,
    "AMDREY19": 0.0,
    "AMDREY20": 0.0,
    "ASTRMASK": "xe.mask"
  }
}