{
  "meta": {
    "source_file": "./data/dss1red-fits/dss1red_XE410.fits",
    "exported_utc": "2026-02-04T15:23:25.377065+00:00",
    "size_bytes": 391985280
  },
  "header": {
    "SIMPLE": true,
    "BITPIX": 16,
    "NAXIS": 2,
    "NAXIS1": 14000,
    "NAXIS2": 13999,
    "DATE": "2006-04-04T16:03:21",
    "ORIGIN": "STScI/MAST",
    "SURVEY": "POSSI-E",
    "REGION": "XE410",
    "PLATEID": "08HY",
    "SCANNUM": "00",
    "DSCNDNUM": "00",
    "TELESCID": 1,
    "BANDPASS": 8,
    "COPYRGHT": "STScI/AURA",
    "SITELAT": 33.356,
    "SITELONG": 116.863,
    "TELESCOP": "Palomar Schmidt",
    "INSTRUME": "Photographic Plate",
    "EMULSION": "103aE",
    "FILTER": "plexi",
    "PLTSCALE": 67.2,
    "PLTSIZEX": 355.0,
    "PLTSIZEY": 355.0,
    "PLATERA": 38.0177670002,
    "PLATEDEC": 18.6446674495,
    "PLTLABEL": "E443",
    "DATE-OBS": "1951-11-30T04:42:00",
    "EXPOSURE": 50.0,
    "PLTGRADE": "1",
    "OBSHA": 1.25,
    "OBSZD": 22.345,
    "AIRMASS": 1.081,
    "REFBETA": 61.8196598237,
    "REFBETAP": -0.082,
    "REFK1": -39314.3602447,
    "REFK2": 0.0,
    "CNPIX1": 0,
    "CNPIX2": 0,
    "XPIXELS": 14000,
    "YPIXELS": 13999,
    "XPIXELSZ": 25.2845,
    "YPIXELSZ": 25.2845,
    "PPO1": 0.0,
    "PPO2": 0.0,
    "PPO3": 177500.0,
    "PPO4": 0.0,
    "PPO5": 0.0,
    "PPO6": 177500.0,
    "PLTRAH": 2,
    "PLTRAM": 32,
    "PLTRAS": 4.26,
    "PLTDECSN": "+",
    "PLTDECD": 18,
    "PLTDECM": 38,
    "PLTDECS": 40.8,
    "EQUINOX": 2000.0,
    "AMDX1": 67.2355901556,
    "AMDX2": 0.510447090107,
    "AMDX3": 47.0476841501,
    "AMDX4": 1.05982633223e-05,
    "AMDX5": 3.2420985026e-07,
    "AMDX6": 2.00176458219e-06,
    "AMDX7": 0.0,
    "AMDX8": 2.19733587376e-06,
    "AMDX9": 4.02824777695e-08,
    "AMDX10": 2.55268168222e-06,
    "AMDX11": -5.07200445246e-08,
    "AMDX12": 0.0,
    "AMDX13": 0.0,
    "AMDX14": 0.0,
    "AMDX15": 0.0,
    "AMDX16": 0.0,
    "AMDX17": 0.0,
    "AMDX18": 0.0,
    "AMDX19": 0.0,
    "AMDX20": 0.0,
    "AMDY1": 67.2534060703,
    "AMDY2": -0.505519342144,
    "AMDY3": -17.5688923594,
    "AMDY4": -2.44203725264e-05,
    "AMDY5": 7.34206519013e-06,
    "AMDY6": -5.02865315547e-06,
    "AMDY7": 0.0,
    "AMDY8": 2.1760486809e-06,
    "AMDY9": -1.93765143076e-07,
    "AMDY10": 2.50381661854e-06,
    "AMDY11": -1.64100460437e-07,
    "AMDY12": 0.0,
    "AMDY13": 0.0,
    "AMDY14": 0.0,
    "AMDY15": 0.0,
    "AMDY16": 0.0,
    "AMDY17": 0.0,
    "AMDY18": 0.0,
    "AMDY19": 0.0,
    "AMDY20": 0.0,
    "AMDREX1": 67.2356932857,
    "AMDREX2": 0.512769158494,
    "AMDREX3": 47.0295746544,
    "AMDREX4": 6.41906770855e-06,
    "AMDREX5": 1.36971201284e-06,
    "AMDREX6": -1.50146913277e-06,
    "AMDREX7": 0.0,
    "AMDREX8": -1.9566109894e-07,
    "AMDREX9": 1.73786869744e-08,
    "AMDREX10": 1.49243380365e-07,
    "AMDREX11": -7.72887448467e-08,
    "AMDREX12": 0.0,
    "AMDREX13": 0.0,
    "AMDREX14": 0.0,
    "AMDREX15": 0.0,
    "AMDREX16": 0.0,
    "AMDREX17": 0.0,
    "AMDREX18": 0.0,
    "AMDREX19": 0.0,
    "AMDREX20": 0.0,
    "AMDREY1": 67.2526087312,
    "AMDREY2": -0.505534748369,
    "AMDREY3": -17.5522005244,
    "AMDREY4": -1.9201083762e-05,
    "AMDREY5": 3.98584845249e-06,
    "AMDREY6": -4.41107538411e-06,
    "AMDREY7": 0.0,
    "AMDREY8": -2.25131152558e-07,
    "AMDREY9": -1.84094008967e-07,
    "AMDREY10": 1.14426318952e-07,
    "AMDREY11": -1.40236871027e-07,
    "AMDREY12": 0.0,
    "AMDREY13": 0.0,
    "AMDREY14": 0.0,
    "AMDREY15": 0.0,
    "AMDREY16": 0.0,
    "AMDREY17": 0.0,
    "AMDREY18": 0.0,
    "AMDREY19": 0.0,
    "AMDREY20": 0.0,
    "ASTRMASK": "xe.mask"
  }
}